{"language":"en","textAngle":-1.8999999999998818,"orientation":"Left","regions":[{"boundingBox":"385,116,1667,192","lines":[{"boundingBox":"385,116,1667,87","words":[{"boundingBox":"385,139,389,63","text":"PLATINUM"},{"boundingBox":"807,132,342,62","text":"PRODUCE"},{"boundingBox":"1176,127,325,76","text":"(Sunshine"},{"boundingBox":"1534,121,221,76","text":"coast)"},{"boundingBox":"1784,122,120,78","text":"Pty"},{"boundingBox":"1929,116,123,64","text":"Ltd"}]},{"boundingBox":"683,225,1064,83","words":[{"boundingBox":"683,235,315,63","text":"wholesale"},{"boundingBox":"1034,233,161,64","text":"fruit"},{"boundingBox":"1226,230,127,60","text":"and"},{"boundingBox":"1381,225,366,83","text":"vegetables"}]}]},{"boundingBox":"291,395,782,692","lines":[{"boundingBox":"296,395,258,33","words":[{"boundingBox":"296,396,156,32","text":"P.O.Box"},{"boundingBox":"464,395,90,33","text":"7377"}]},{"boundingBox":"296,442,465,42","words":[{"boundingBox":"296,443,114,41","text":"Sippy"},{"boundingBox":"419,443,144,38","text":"Downs,"},{"boundingBox":"578,442,71,35","text":"QId"},{"boundingBox":"667,442,94,32","text":"4556"}]},{"boundingBox":"296,489,519,35","words":[{"boundingBox":"296,490,70,34","text":"Lee"},{"boundingBox":"378,490,155,33","text":"Belcher"},{"boundingBox":"541,498,13,25","text":":"},{"boundingBox":"567,490,86,33","text":"0411"},{"boundingBox":"667,490,68,32","text":"554"},{"boundingBox":"745,489,70,33","text":"415"}]},{"boundingBox":"296,537,533,35","words":[{"boundingBox":"296,539,98,33","text":"Brett"},{"boundingBox":"403,538,164,33","text":"Belcher:"},{"boundingBox":"580,539,91,32","text":"0403"},{"boundingBox":"683,538,70,33","text":"057"},{"boundingBox":"764,537,65,34","text":"721"}]},{"boundingBox":"296,586,377,42","words":[{"boundingBox":"296,587,85,33","text":"Fax:"},{"boundingBox":"392,587,72,41","text":"(07)"},{"boundingBox":"478,586,91,33","text":"5478"},{"boundingBox":"582,586,91,33","text":"1697"}]},{"boundingBox":"296,634,649,43","words":[{"boundingBox":"296,634,649,43","text":"admin@platinumproduce.com.au"}]},{"boundingBox":"292,837,781,37","words":[{"boundingBox":"292,837,227,37","text":"Alexandra"},{"boundingBox":"532,838,104,36","text":"Park"},{"boundingBox":"648,838,268,36","text":"Conferrence"},{"boundingBox":"930,838,143,36","text":"Centre"}]},{"boundingBox":"295,890,259,38","words":[{"boundingBox":"295,890,66,37","text":"PO"},{"boundingBox":"374,891,91,36","text":"Box"},{"boundingBox":"478,892,76,36","text":"705"}]},{"boundingBox":"296,997,464,40","words":[{"boundingBox":"296,997,148,36","text":"Cotton"},{"boundingBox":"460,998,95,36","text":"Tree"},{"boundingBox":"570,998,79,39","text":"Qid"},{"boundingBox":"657,999,103,35","text":"4558"}]},{"boundingBox":"291,1050,203,37","words":[{"boundingBox":"291,1050,203,37","text":"Australia"}]}]},{"boundingBox":"1415,407,611,539","lines":[{"boundingBox":"1544,407,478,73","words":[{"boundingBox":"1544,412,149,68","text":"Tax"},{"boundingBox":"1713,407,309,72","text":"Invoice"}]},{"boundingBox":"1511,527,140,34","words":[{"boundingBox":"1511,527,140,34","text":"Invoice"}]},{"boundingBox":"1551,585,412,36","words":[{"boundingBox":"1551,587,167,34","text":"AB.N.41"},{"boundingBox":"1814,586,69,33","text":"536"},{"boundingBox":"1895,585,68,33","text":"406"}]},{"boundingBox":"1419,754,113,31","words":[{"boundingBox":"1419,754,63,31","text":"Ship"},{"boundingBox":"1493,755,39,25","text":"To:"}]},{"boundingBox":"1415,833,611,30","words":[{"boundingBox":"1415,834,174,28","text":"Alexandra"},{"boundingBox":"1599,834,79,29","text":"Park"},{"boundingBox":"1689,834,212,29","text":"Conference"},{"boundingBox":"1912,833,114,29","text":"Centre"}]},{"boundingBox":"1419,875,236,29","words":[{"boundingBox":"1419,875,38,28","text":"13"},{"boundingBox":"1466,876,76,28","text":"Mari"},{"boundingBox":"1550,876,105,28","text":"Street"}]},{"boundingBox":"1415,915,559,31","words":[{"boundingBox":"1415,916,174,29","text":"Alexan&a"},{"boundingBox":"1599,917,193,29","text":"Healdlands"},{"boundingBox":"1891,915,83,31","text":"4572"}]}]},{"boundingBox":"391,1173,69,984","lines":[{"boundingBox":"445,1173,14,26","words":[{"boundingBox":"445,1173,14,26","text":"1"}]},{"boundingBox":"445,1218,14,26","words":[{"boundingBox":"445,1218,14,26","text":"1"}]},{"boundingBox":"445,1264,14,25","words":[{"boundingBox":"445,1264,14,25","text":"1"}]},{"boundingBox":"427,1355,33,24","words":[{"boundingBox":"427,1355,33,24","text":"15"}]},{"boundingBox":"444,1400,14,25","words":[{"boundingBox":"444,1400,14,25","text":"1"}]},{"boundingBox":"442,1493,14,25","words":[{"boundingBox":"442,1493,14,25","text":"1"}]},{"boundingBox":"442,1539,13,25","words":[{"boundingBox":"442,1539,13,25","text":"1"}]},{"boundingBox":"441,1585,14,26","words":[{"boundingBox":"441,1585,14,26","text":"1"}]},{"boundingBox":"391,2138,67,19","words":[{"boundingBox":"391,2138,67,19","text":"CHEC"}]}]},{"boundingBox":"546,1174,114,436","lines":[{"boundingBox":"558,1174,97,25","words":[{"boundingBox":"558,1174,97,25","text":"FA130"}]},{"boundingBox":"556,1219,96,24","words":[{"boundingBox":"556,1219,39,24","text":"FB"},{"boundingBox":"605,1219,47,24","text":"101"}]},{"boundingBox":"553,1264,102,26","words":[{"boundingBox":"553,1264,45,26","text":"FM"},{"boundingBox":"608,1264,47,25","text":"101"}]},{"boundingBox":"555,1310,102,25","words":[{"boundingBox":"555,1310,41,25","text":"FR"},{"boundingBox":"606,1311,51,24","text":"105"}]},{"boundingBox":"554,1355,101,25","words":[{"boundingBox":"554,1355,42,25","text":"w"},{"boundingBox":"604,1356,51,24","text":"105"}]},{"boundingBox":"554,1400,101,26","words":[{"boundingBox":"554,1400,43,26","text":"VT"},{"boundingBox":"605,1401,50,25","text":"114"}]},{"boundingBox":"552,1447,103,25","words":[{"boundingBox":"552,1447,44,25","text":"vc"},{"boundingBox":"607,1447,48,25","text":"118"}]},{"boundingBox":"551,1492,106,26","words":[{"boundingBox":"551,1492,44,26","text":"PO"},{"boundingBox":"606,1493,51,25","text":"105"}]},{"boundingBox":"546,1538,114,26","words":[{"boundingBox":"546,1538,52,26","text":"MM"},{"boundingBox":"609,1539,51,25","text":"109"}]},{"boundingBox":"551,1584,103,26","words":[{"boundingBox":"551,1584,41,26","text":"FH"},{"boundingBox":"604,1584,50,26","text":"102"}]}]},{"boundingBox":"757,1173,439,725","lines":[{"boundingBox":"759,1173,361,31","words":[{"boundingBox":"759,1174,132,30","text":"Pink}adys"},{"boundingBox":"898,1186,13,5","text":"-"},{"boundingBox":"918,1173,103,30","text":"Speciaf"},{"boundingBox":"1027,1173,93,25","text":"Carton"}]},{"boundingBox":"759,1218,395,25","words":[{"boundingBox":"759,1219,123,24","text":"Bananas"},{"boundingBox":"888,1231,13,6","text":"-"},{"boundingBox":"908,1218,144,25","text":"Cave-dish"},{"boundingBox":"1061,1218,93,24","text":"Carton"}]},{"boundingBox":"759,1263,351,31","words":[{"boundingBox":"759,1264,145,25","text":"Mandahns"},{"boundingBox":"910,1277,12,5","text":"-"},{"boundingBox":"928,1264,79,30","text":"Large"},{"boundingBox":"1016,1263,94,25","text":"Carton"}]},{"boundingBox":"759,1310,257,29","words":[{"boundingBox":"759,1310,169,25","text":"Rockme$ons"},{"boundingBox":"934,1322,14,5","text":"-"},{"boundingBox":"955,1310,61,29","text":"Tray"}]},{"boundingBox":"761,1355,360,30","words":[{"boundingBox":"761,1355,133,25","text":"Tomatoes"},{"boundingBox":"900,1368,12,5","text":"-"},{"boundingBox":"920,1355,93,30","text":"Cherry"},{"boundingBox":"1018,1355,103,24","text":"Punnet"}]},{"boundingBox":"761,1400,435,30","words":[{"boundingBox":"761,1401,132,24","text":"Tomatoes"},{"boundingBox":"898,1413,13,5","text":"-"},{"boundingBox":"918,1400,82,25","text":"Rorna"},{"boundingBox":"1008,1400,132,30","text":"Economy"},{"boundingBox":"1148,1400,48,24","text":"Ctn"}]},{"boundingBox":"760,1446,404,31","words":[{"boundingBox":"760,1446,157,26","text":"Cucumbers"},{"boundingBox":"921,1459,13,5","text":"-"},{"boundingBox":"942,1446,159,25","text":"Continental"},{"boundingBox":"1106,1447,58,30","text":"Bag"}]},{"boundingBox":"759,1492,243,30","words":[{"boundingBox":"759,1492,97,25","text":"Onims"},{"boundingBox":"862,1506,12,4","text":"-"},{"boundingBox":"882,1492,58,25","text":"Red"},{"boundingBox":"947,1492,55,30","text":"Bag"}]},{"boundingBox":"758,1538,394,30","words":[{"boundingBox":"758,1538,121,25","text":"Mescufn"},{"boundingBox":"886,1539,52,29","text":"Ekg"},{"boundingBox":"946,1538,48,27","text":"QE"},{"boundingBox":"1059,1538,93,25","text":"Carton"}]},{"boundingBox":"757,1584,265,31","words":[{"boundingBox":"757,1584,147,31","text":"Honey±w"},{"boundingBox":"910,1597,12,5","text":"-"},{"boundingBox":"930,1584,92,25","text":"Carton"}]},{"boundingBox":"767,1829,224,25","words":[{"boundingBox":"767,1829,37,24","text":"TO"},{"boundingBox":"811,1829,35,23","text":"BE"},{"boundingBox":"852,1830,139,24","text":"ChAAGEO"}]},{"boundingBox":"835,1870,86,28","words":[{"boundingBox":"835,1870,86,28","text":"Project"}]}]},{"boundingBox":"234,2418,838,488","lines":[{"boundingBox":"264,2418,519,40","words":[{"boundingBox":"264,2423,51,32","text":"No"},{"boundingBox":"326,2423,101,31","text":"Claim"},{"boundingBox":"437,2419,216,39","text":"Recognised"},{"boundingBox":"662,2418,121,31","text":"Unless"}]},{"boundingBox":"261,2463,472,41","words":[{"boundingBox":"261,2468,35,31","text":"in"},{"boundingBox":"309,2466,129,38","text":"Writing"},{"boundingBox":"448,2465,112,31","text":"Within"},{"boundingBox":"571,2464,44,30","text":"24"},{"boundingBox":"623,2463,110,31","text":"Hours"}]},{"boundingBox":"263,2506,516,37","words":[{"boundingBox":"263,2512,65,31","text":"The"},{"boundingBox":"334,2511,118,30","text":"Above"},{"boundingBox":"462,2507,192,33","text":"Mentioned"},{"boundingBox":"662,2506,117,31","text":"Goods"}]},{"boundingBox":"258,2552,404,35","words":[{"boundingBox":"258,2564,57,23","text":"are"},{"boundingBox":"324,2555,35,32","text":"in"},{"boundingBox":"371,2554,102,32","text":"Good"},{"boundingBox":"481,2554,104,31","text":"Order"},{"boundingBox":"591,2552,71,32","text":"and"}]},{"boundingBox":"259,2600,174,32","words":[{"boundingBox":"259,2600,174,32","text":"Condition"}]},{"boundingBox":"243,2683,253,35","words":[{"boundingBox":"243,2685,99,33","text":"Bank"},{"boundingBox":"350,2683,146,34","text":"Details:"}]},{"boundingBox":"241,2724,831,44","words":[{"boundingBox":"241,2731,168,34","text":"Platinum"},{"boundingBox":"420,2729,159,34","text":"Produce"},{"boundingBox":"590,2728,18,40","text":"("},{"boundingBox":"614,2726,178,34","text":"Sunshine"},{"boundingBox":"803,2725,119,39","text":"Coast)"},{"boundingBox":"934,2725,64,39","text":"Pty"},{"boundingBox":"1007,2724,65,31","text":"Ltd"}]},{"boundingBox":"241,2773,525,42","words":[{"boundingBox":"241,2777,295,34","text":"Commonwealth"},{"boundingBox":"546,2776,99,32","text":"Bank"},{"boundingBox":"654,2773,112,42","text":"(CBA)"}]},{"boundingBox":"238,2824,242,35","words":[{"boundingBox":"238,2826,98,33","text":"BSE:"},{"boundingBox":"346,2824,134,33","text":"064239"}]},{"boundingBox":"234,2871,257,35","words":[{"boundingBox":"234,2872,73,34","text":"A/C"},{"boundingBox":"319,2871,172,34","text":"10112209"}]}]},{"boundingBox":"1405,1072,288,1608","lines":[{"boundingBox":"1498,1072,140,37","words":[{"boundingBox":"1498,1072,140,37","text":"C.O.D."}]},{"boundingBox":"1431,1172,97,26","words":[{"boundingBox":"1431,1172,97,26","text":"sex"}]},{"boundingBox":"1432,1217,96,26","words":[{"boundingBox":"1432,1217,96,26","text":"secc"}]},{"boundingBox":"1432,1309,96,26","words":[{"boundingBox":"1432,1309,96,26","text":"EZCC"}]},{"boundingBox":"1432,1400,96,26","words":[{"boundingBox":"1432,1400,96,26","text":"stg-cc"}]},{"boundingBox":"1433,1446,96,26","words":[{"boundingBox":"1433,1446,96,26","text":"S24-co"}]},{"boundingBox":"1433,1492,95,26","words":[{"boundingBox":"1433,1492,95,26","text":"SZCC"}]},{"boundingBox":"1432,1538,97,27","words":[{"boundingBox":"1432,1538,97,27","text":"seco"}]},{"boundingBox":"1433,1584,97,26","words":[{"boundingBox":"1433,1584,97,26","text":"S12C0"}]},{"boundingBox":"1625,2461,68,28","words":[{"boundingBox":"1625,2461,68,28","text":"CST"}]},{"boundingBox":"1405,2638,285,42","words":[{"boundingBox":"1405,2638,181,40","text":"Balance"},{"boundingBox":"1602,2640,88,40","text":"Due"}]}]},{"boundingBox":"1778,1218,267,1469","lines":[{"boundingBox":"1786,1218,98,27","words":[{"boundingBox":"1786,1218,98,27","text":"S22.N"}]},{"boundingBox":"1786,1263,97,28","words":[{"boundingBox":"1786,1263,97,28","text":"sszco"}]},{"boundingBox":"1786,1400,99,27","words":[{"boundingBox":"1786,1400,99,27","text":"S-fCO"}]},{"boundingBox":"1787,1492,99,28","words":[{"boundingBox":"1787,1492,99,28","text":"sacc"}]},{"boundingBox":"1788,1584,98,27","words":[{"boundingBox":"1788,1584,98,27","text":"Sf2éV"}]},{"boundingBox":"1899,2464,80,31","words":[{"boundingBox":"1899,2464,80,31","text":"smoo"}]},{"boundingBox":"1901,2508,81,31","words":[{"boundingBox":"1901,2508,81,31","text":"seoo"}]},{"boundingBox":"1778,2617,267,70","words":[{"boundingBox":"1778,2617,267,70","text":"$274.00"}]}]},{"boundingBox":"1479,2806,385,49","lines":[{"boundingBox":"1479,2806,116,35","words":[{"boundingBox":"1479,2806,116,35","text":"Boxes"}]},{"boundingBox":"1769,2811,95,44","words":[{"boundingBox":"1769,2811,95,44","text":"Bags"}]}]}]}