{"language":"en","textAngle":0.0,"orientation":"Down","regions":[{"boundingBox":"469,469,402,1183","lines":[{"boundingBox":"470,469,155,26","words":[{"boundingBox":"470,469,72,25","text":"Roger"},{"boundingBox":"546,471,79,24","text":"Jordan"}]},{"boundingBox":"472,505,199,24","words":[{"boundingBox":"472,505,102,22","text":"Mathilda"},{"boundingBox":"582,507,89,22","text":"Avenue"}]},{"boundingBox":"471,535,337,27","words":[{"boundingBox":"471,535,132,25","text":"Sunnyvale,"},{"boundingBox":"612,538,113,22","text":"Califomia"},{"boundingBox":"734,541,74,21","text":"93231"}]},{"boundingBox":"471,570,187,24","words":[{"boundingBox":"471,570,63,24","text":"(643)"},{"boundingBox":"545,572,113,22","text":"132-9843"}]},{"boundingBox":"471,795,346,46","words":[{"boundingBox":"471,795,122,34","text":"Some"},{"boundingBox":"610,798,207,43","text":"Company"}]},{"boundingBox":"469,836,307,44","words":[{"boundingBox":"469,836,64,34","text":"c/o"},{"boundingBox":"551,837,121,33","text":"Some"},{"boundingBox":"689,839,87,41","text":"Guy"}]},{"boundingBox":"548,1074,258,28","words":[{"boundingBox":"548,1074,34,20","text":"Pie"},{"boundingBox":"590,1075,95,25","text":"Cottage"},{"boundingBox":"694,1076,15,20","text":"6"},{"boundingBox":"716,1077,16,19","text":"X"},{"boundingBox":"741,1077,65,25","text":"2.4kg"}]},{"boundingBox":"480,1111,391,46","words":[{"boundingBox":"480,1111,60,20","text":"Tetra"},{"boundingBox":"547,1112,59,24","text":"Juice"},{"boundingBox":"615,1113,88,44","text":"Orant?"},{"boundingBox":"713,1114,66,20","text":"100%"},{"boundingBox":"789,1115,82,25","text":"Popper"}]},{"boundingBox":"501,1186,348,26","words":[{"boundingBox":"501,1186,74,21","text":"Sauce"},{"boundingBox":"583,1187,44,25","text":"Soy"},{"boundingBox":"636,1188,124,21","text":"Mushroom"},{"boundingBox":"770,1190,44,19","text":"600"},{"boundingBox":"823,1190,26,20","text":"Ml"}]},{"boundingBox":"503,1224,344,29","words":[{"boundingBox":"503,1224,79,20","text":"Biscuit"},{"boundingBox":"591,1225,80,20","text":"Crumb"},{"boundingBox":"679,1226,58,20","text":"Base"},{"boundingBox":"746,1227,39,19","text":"Mix"},{"boundingBox":"795,1227,13,20","text":"5"},{"boundingBox":"818,1227,29,26","text":"Kg"}]},{"boundingBox":"497,1261,354,23","words":[{"boundingBox":"497,1261,161,21","text":"Breadcrumbs"},{"boundingBox":"667,1263,79,20","text":"Gluten"},{"boundingBox":"755,1264,49,20","text":"Free"},{"boundingBox":"812,1265,15,19","text":"4"},{"boundingBox":"835,1265,16,19","text":"X"}]},{"boundingBox":"641,1287,66,24","words":[{"boundingBox":"641,1287,66,24","text":"2.5kg"}]},{"boundingBox":"477,1322,392,28","words":[{"boundingBox":"477,1322,59,21","text":"Cake"},{"boundingBox":"545,1323,34,22","text":"P/c"},{"boundingBox":"587,1324,69,25","text":"Apple"},{"boundingBox":"665,1325,85,20","text":"Crunch"},{"boundingBox":"757,1326,50,24","text":"Tray"},{"boundingBox":"815,1327,30,18","text":"40"},{"boundingBox":"854,1327,15,19","text":"X"}]},{"boundingBox":"646,1349,57,24","words":[{"boundingBox":"646,1349,57,24","text":"88gr"}]},{"boundingBox":"529,1384,287,27","words":[{"boundingBox":"529,1384,87,22","text":"Brussel"},{"boundingBox":"626,1385,91,24","text":"Sprouts"},{"boundingBox":"726,1385,31,25","text":"Iqf"},{"boundingBox":"764,1386,13,20","text":"2"},{"boundingBox":"787,1386,29,25","text":"Kg"}]},{"boundingBox":"492,1422,358,27","words":[{"boundingBox":"492,1422,127,21","text":"Deodorant"},{"boundingBox":"627,1423,85,20","text":"Tablets"},{"boundingBox":"721,1423,69,21","text":"Urinal"},{"boundingBox":"798,1424,14,20","text":"4"},{"boundingBox":"822,1425,28,24","text":"Kg"}]},{"boundingBox":"469,1459,402,25","words":[{"boundingBox":"469,1459,71,21","text":"Bread"},{"boundingBox":"549,1459,71,21","text":"Sliced"},{"boundingBox":"630,1461,70,23","text":"Super"},{"boundingBox":"706,1460,65,20","text":"Thick"},{"boundingBox":"779,1461,69,20","text":"White"},{"boundingBox":"856,1462,15,19","text":"6"}]},{"boundingBox":"624,1484,96,25","words":[{"boundingBox":"624,1484,16,20","text":"X"},{"boundingBox":"648,1485,72,24","text":"700gr"}]},{"boundingBox":"672,1596,55,19","words":[{"boundingBox":"672,1596,55,19","text":"Total"}]},{"boundingBox":"625,1633,150,19","words":[{"boundingBox":"625,1633,93,19","text":"Balance"},{"boundingBox":"729,1633,46,19","text":"Due"}]}]},{"boundingBox":"1597,824,144,93","lines":[{"boundingBox":"1616,824,107,19","words":[{"boundingBox":"1616,824,82,19","text":"Invoice"},{"boundingBox":"1707,826,16,17","text":"#"}]},{"boundingBox":"1643,860,54,20","words":[{"boundingBox":"1643,860,54,20","text":"Date"}]},{"boundingBox":"1597,897,144,20","words":[{"boundingBox":"1597,897,90,20","text":"Amount"},{"boundingBox":"1697,899,44,18","text":"Due"}]}]},{"boundingBox":"1020,1027,93,468","lines":[{"boundingBox":"1039,1027,61,20","words":[{"boundingBox":"1039,1027,61,20","text":"code"}]},{"boundingBox":"1025,1081,88,20","words":[{"boundingBox":"1025,1081,88,20","text":"156208"}]},{"boundingBox":"1032,1130,73,20","words":[{"boundingBox":"1032,1130,73,20","text":"74888"}]},{"boundingBox":"1030,1193,74,20","words":[{"boundingBox":"1030,1193,74,20","text":"48707"}]},{"boundingBox":"1039,1230,57,21","words":[{"boundingBox":"1039,1230,57,21","text":"1292"}]},{"boundingBox":"1023,1279,87,20","words":[{"boundingBox":"1023,1279,87,20","text":"140797"}]},{"boundingBox":"1029,1339,73,20","words":[{"boundingBox":"1029,1339,73,20","text":"26787"}]},{"boundingBox":"1022,1389,87,19","words":[{"boundingBox":"1022,1389,87,19","text":"136245"}]},{"boundingBox":"1021,1426,88,20","words":[{"boundingBox":"1021,1426,88,20","text":"128905"}]},{"boundingBox":"1020,1475,88,20","words":[{"boundingBox":"1020,1475,88,20","text":"140199"}]}]},{"boundingBox":"1304,1032,192,626","lines":[{"boundingBox":"1372,1032,124,20","words":[{"boundingBox":"1372,1032,124,20","text":"Delivered"}]},{"boundingBox":"1401,1086,65,21","words":[{"boundingBox":"1401,1086,65,21","text":"15.00"}]},{"boundingBox":"1408,1135,50,20","words":[{"boundingBox":"1408,1135,50,20","text":"1.00"}]},{"boundingBox":"1407,1197,50,20","words":[{"boundingBox":"1407,1197,50,20","text":"1.00"}]},{"boundingBox":"1407,1235,50,19","words":[{"boundingBox":"1407,1235,50,19","text":"1.70"}]},{"boundingBox":"1406,1283,50,20","words":[{"boundingBox":"1406,1283,50,20","text":"1.00"}]},{"boundingBox":"1405,1343,51,20","words":[{"boundingBox":"1405,1343,51,20","text":"5.00"}]},{"boundingBox":"1404,1392,51,19","words":[{"boundingBox":"1404,1392,51,19","text":"2.00"}]},{"boundingBox":"1405,1429,49,20","words":[{"boundingBox":"1405,1429,49,20","text":"1.00"}]},{"boundingBox":"1404,1478,50,19","words":[{"boundingBox":"1404,1478,50,19","text":"1.00"}]},{"boundingBox":"1304,1598,94,22","words":[{"boundingBox":"1304,1598,94,22","text":"$3657.7"}]},{"boundingBox":"1370,1635,29,23","words":[{"boundingBox":"1370,1635,29,23","text":"$0"}]}]},{"boundingBox":"1755,1091,79,411","lines":[{"boundingBox":"1755,1091,79,22","words":[{"boundingBox":"1755,1091,79,22","text":"$189.6"}]},{"boundingBox":"1769,1139,49,23","words":[{"boundingBox":"1769,1139,49,23","text":"$3.2"}]},{"boundingBox":"1769,1201,50,23","words":[{"boundingBox":"1769,1201,50,23","text":"$3.6"}]},{"boundingBox":"1760,1239,65,22","words":[{"boundingBox":"1760,1239,65,22","text":"$61.4"}]},{"boundingBox":"1760,1287,64,22","words":[{"boundingBox":"1760,1287,64,22","text":"$55.9"}]},{"boundingBox":"1759,1347,64,22","words":[{"boundingBox":"1759,1347,64,22","text":"$44.7"}]},{"boundingBox":"1766,1395,49,23","words":[{"boundingBox":"1766,1395,49,23","text":"$9.7"}]},{"boundingBox":"1758,1432,65,23","words":[{"boundingBox":"1758,1432,65,23","text":"$59.4"}]},{"boundingBox":"1757,1481,65,21","words":[{"boundingBox":"1757,1481,65,21","text":"$21.9"}]}]},{"boundingBox":"1878,830,341,964","lines":[{"boundingBox":"2087,830,86,20","words":[{"boundingBox":"2087,830,86,20","text":"101138"}]},{"boundingBox":"2035,866,184,25","words":[{"boundingBox":"2035,866,90,25","text":"January"},{"boundingBox":"2134,867,20,22","text":"1,"},{"boundingBox":"2162,867,57,21","text":"2012"}]},{"boundingBox":"2081,904,94,21","words":[{"boundingBox":"2081,904,94,21","text":"$3657.7"}]},{"boundingBox":"2092,1042,124,20","words":[{"boundingBox":"2092,1042,124,20","text":"Total/unit"}]},{"boundingBox":"2114,1096,79,21","words":[{"boundingBox":"2114,1096,79,21","text":"$208.5"}]},{"boundingBox":"2128,1143,49,22","words":[{"boundingBox":"2128,1143,49,22","text":"$3.2"}]},{"boundingBox":"2127,1206,50,21","words":[{"boundingBox":"2127,1206,50,21","text":"$3.6"}]},{"boundingBox":"2119,1243,66,22","words":[{"boundingBox":"2119,1243,66,22","text":"$67.6"}]},{"boundingBox":"2119,1292,65,21","words":[{"boundingBox":"2119,1292,65,21","text":"$55.9"}]},{"boundingBox":"2119,1351,63,21","words":[{"boundingBox":"2119,1351,63,21","text":"549.2"}]},{"boundingBox":"2124,1399,51,21","words":[{"boundingBox":"2124,1399,51,21","text":"$9.7"}]},{"boundingBox":"2117,1436,65,21","words":[{"boundingBox":"2117,1436,65,21","text":"$65.4"}]},{"boundingBox":"2117,1485,65,21","words":[{"boundingBox":"2117,1485,65,21","text":"$21.9"}]},{"boundingBox":"1878,1767,174,27","words":[{"boundingBox":"1878,1767,174,27","text":"NOTES"}]}]},{"boundingBox":"2427,1045,174,465","lines":[{"boundingBox":"2427,1045,174,20","words":[{"boundingBox":"2427,1045,104,19","text":"Pre-GST"},{"boundingBox":"2539,1047,62,18","text":"Total"}]},{"boundingBox":"2467,1100,94,21","words":[{"boundingBox":"2467,1100,94,21","text":"$2843.3"}]},{"boundingBox":"2488,1148,49,21","words":[{"boundingBox":"2488,1148,49,21","text":"$3.2"}]},{"boundingBox":"2487,1209,50,23","words":[{"boundingBox":"2487,1209,50,23","text":"$3.6"}]},{"boundingBox":"2472,1247,79,22","words":[{"boundingBox":"2472,1247,79,22","text":"$104.4"}]},{"boundingBox":"2478,1295,66,22","words":[{"boundingBox":"2478,1295,66,22","text":"$55.9"}]},{"boundingBox":"2470,1355,79,21","words":[{"boundingBox":"2470,1355,79,21","text":"$223.5"}]},{"boundingBox":"2477,1403,65,21","words":[{"boundingBox":"2477,1403,65,21","text":"$19.5"}]},{"boundingBox":"2476,1440,66,22","words":[{"boundingBox":"2476,1440,66,22","text":"$59.4"}]},{"boundingBox":"2476,1488,65,22","words":[{"boundingBox":"2476,1488,65,22","text":"$21.9"}]}]},{"boundingBox":"2828,1050,94,465","lines":[{"boundingBox":"2844,1050,62,19","words":[{"boundingBox":"2844,1050,62,19","text":"Total"}]},{"boundingBox":"2828,1104,94,21","words":[{"boundingBox":"2828,1104,94,21","text":"$3127.6"}]},{"boundingBox":"2849,1152,49,23","words":[{"boundingBox":"2849,1152,49,23","text":"$3.2"}]},{"boundingBox":"2848,1214,50,22","words":[{"boundingBox":"2848,1214,50,22","text":"$3.6"}]},{"boundingBox":"2833,1250,79,23","words":[{"boundingBox":"2833,1250,79,23","text":"$114.8"}]},{"boundingBox":"2840,1299,65,23","words":[{"boundingBox":"2840,1299,65,23","text":"$55.9"}]},{"boundingBox":"2832,1359,79,22","words":[{"boundingBox":"2832,1359,79,22","text":"$245.9"}]},{"boundingBox":"2839,1407,63,22","words":[{"boundingBox":"2839,1407,63,22","text":"$19.5"}]},{"boundingBox":"2838,1445,65,21","words":[{"boundingBox":"2838,1445,65,21","text":"$65.4"}]},{"boundingBox":"2838,1492,65,23","words":[{"boundingBox":"2838,1492,65,23","text":"$21.9"}]}]},{"boundingBox":"450,1765,1384,100","lines":[{"boundingBox":"1480,1765,354,27","words":[{"boundingBox":"1480,1765,354,27","text":"ADDITIONAL"}]},{"boundingBox":"450,1830,1161,35","words":[{"boundingBox":"450,1834,23,26","text":"A"},{"boundingBox":"483,1833,120,27","text":"finance"},{"boundingBox":"614,1833,111,32","text":"charge"},{"boundingBox":"737,1831,32,28","text":"of"},{"boundingBox":"780,1831,78,28","text":"1.5%"},{"boundingBox":"870,1831,50,27","text":"will"},{"boundingBox":"933,1831,38,26","text":"be"},{"boundingBox":"983,1830,88,27","text":"made"},{"boundingBox":"1082,1836,38,21","text":"on"},{"boundingBox":"1132,1830,106,32","text":"unpaid"},{"boundingBox":"1250,1830,137,27","text":"balances"},{"boundingBox":"1399,1831,73,26","text":"after"},{"boundingBox":"1482,1831,38,27","text":"30"},{"boundingBox":"1531,1831,80,32","text":"days."}]}]}]}