{"language":"en","textAngle":0.0,"orientation":"Up","regions":[{"boundingBox":"322,278,445,290","lines":[{"boundingBox":"387,278,178,25","words":[{"boundingBox":"387,278,83,21","text":"Roger"},{"boundingBox":"473,286,73,17","text":"Jorcta"},{"boundingBox":"549,292,16,11","text":"n"}]},{"boundingBox":"381,302,232,27","words":[{"boundingBox":"381,302,68,21","text":"Math"},{"boundingBox":"452,309,47,16","text":"'Ida"},{"boundingBox":"510,313,103,16","text":"Avenue"}]},{"boundingBox":"374,323,393,30","words":[{"boundingBox":"374,323,154,26","text":"Sunnyvaje,"},{"boundingBox":"541,334,130,17","text":"California"},{"boundingBox":"683,337,84,16","text":"93231"}]},{"boundingBox":"369,348,220,27","words":[{"boundingBox":"369,348,75,23","text":"(643)"},{"boundingBox":"456,356,133,19","text":"132-9843"}]},{"boundingBox":"330,490,428,47","words":[{"boundingBox":"330,490,153,33","text":"Sorne"},{"boundingBox":"503,500,255,37","text":"Cornpany"}]},{"boundingBox":"322,525,380,43","words":[{"boundingBox":"322,525,81,27","text":"c/o"},{"boundingBox":"423,529,152,29","text":"Sorne"},{"boundingBox":"595,535,107,33","text":"Guy"}]}]},{"boundingBox":"1526,519,136,18","lines":[{"boundingBox":"1526,519,136,18","words":[{"boundingBox":"1526,520,103,17","text":"Invoice"},{"boundingBox":"1641,519,21,16","text":"#"}]}]},{"boundingBox":"1806,500,286,32","lines":[{"boundingBox":"1806,500,286,32","words":[{"boundingBox":"1806,516,70,16","text":"Date"},{"boundingBox":"1905,505,118,22","text":"Afnount"},{"boundingBox":"2033,500,59,17","text":"Due"}]}]},{"boundingBox":"1529,551,574,186","lines":[{"boundingBox":"1557,551,336,25","words":[{"boundingBox":"1557,558,110,17","text":"10113B"},{"boundingBox":"1683,558,112,18","text":"January"},{"boundingBox":"1807,554,27,17","text":"1."},{"boundingBox":"1845,551,48,18","text":"202"}]},{"boundingBox":"1529,693,574,44","words":[{"boundingBox":"1529,716,60,21","text":"Qty"},{"boundingBox":"1608,715,72,18","text":"Unit"},{"boundingBox":"1691,714,44,23","text":"pri"},{"boundingBox":"1899,705,100,19","text":"Value"},{"boundingBox":"2014,693,89,23","text":"Total"}]}]},{"boundingBox":"479,717,848,482","lines":[{"boundingBox":"1035,717,286,23","words":[{"boundingBox":"1035,717,76,18","text":"'tern"},{"boundingBox":"1125,718,196,22","text":"Description"}]},{"boundingBox":"818,788,504,24","words":[{"boundingBox":"818,788,61,19","text":"Milk"},{"boundingBox":"892,790,53,18","text":"Uht"},{"boundingBox":"957,791,63,19","text":"Iced"},{"boundingBox":"1032,792,100,20","text":"Coffee"},{"boundingBox":"1144,793,38,19","text":"24"},{"boundingBox":"1193,794,19,17","text":"X"},{"boundingBox":"1225,792,97,20","text":"375m1"}]},{"boundingBox":"991,836,331,24","words":[{"boundingBox":"991,836,83,19","text":"Paste"},{"boundingBox":"1086,837,86,23","text":"Curry"},{"boundingBox":"1184,837,57,19","text":"Red"},{"boundingBox":"1255,838,15,17","text":"1"},{"boundingBox":"1285,837,37,23","text":"Kg"}]},{"boundingBox":"574,873,749,32","words":[{"boundingBox":"574,873,75,20","text":"Beef"},{"boundingBox":"657,874,133,25","text":"Striploin"},{"boundingBox":"803,878,98,21","text":"Whole"},{"boundingBox":"913,880,108,20","text":"Chilled"},{"boundingBox":"1034,882,70,23","text":"(app"},{"boundingBox":"1116,882,77,23","text":"20kg"},{"boundingBox":"1206,882,65,21","text":"Ctn)"},{"boundingBox":"1286,882,37,22","text":"Kg"}]},{"boundingBox":"684,921,642,30","words":[{"boundingBox":"684,921,127,21","text":"Chicken"},{"boundingBox":"825,925,108,20","text":"Riblets"},{"boundingBox":"946,927,56,19","text":"Hot"},{"boundingBox":"1013,927,23,20","text":"&"},{"boundingBox":"1049,927,85,24","text":"Spicy"},{"boundingBox":"1147,928,38,19","text":"24"},{"boundingBox":"1197,928,21,19","text":"X"},{"boundingBox":"1232,928,94,22","text":"125gr"}]},{"boundingBox":"813,971,512,24","words":[{"boundingBox":"813,971,79,21","text":"Pizza"},{"boundingBox":"906,973,94,21","text":"Bases"},{"boundingBox":"1014,974,32,20","text":"9\""},{"boundingBox":"1059,974,107,21","text":"Gluten"},{"boundingBox":"1180,975,67,20","text":"Free"},{"boundingBox":"1260,975,65,20","text":"20's"}]},{"boundingBox":"479,1012,846,35","words":[{"boundingBox":"479,1012,92,22","text":"Lamb"},{"boundingBox":"583,1014,131,27","text":"Carvery"},{"boundingBox":"725,1016,63,22","text":"Ckd"},{"boundingBox":"801,1018,73,27","text":"(app"},{"boundingBox":"889,1020,77,26","text":"10kg"},{"boundingBox":"980,1021,67,24","text":"Ctn)"},{"boundingBox":"1060,1022,52,21","text":"4-5"},{"boundingBox":"1127,1022,145,23","text":"Units/ctn"},{"boundingBox":"1286,1022,39,25","text":"Kg"}]},{"boundingBox":"1034,1071,291,25","words":[{"boundingBox":"1034,1071,63,21","text":"Salt"},{"boundingBox":"1109,1071,130,22","text":"Chicken"},{"boundingBox":"1255,1072,15,20","text":"1"},{"boundingBox":"1286,1072,39,24","text":"Kg"}]},{"boundingBox":"988,1122,339,25","words":[{"boundingBox":"988,1122,55,21","text":"Tea"},{"boundingBox":"1058,1123,52,20","text":"Pot"},{"boundingBox":"1122,1123,81,24","text":"Bags"},{"boundingBox":"1218,1122,109,22","text":"1000's"}]},{"boundingBox":"633,1167,694,32","words":[{"boundingBox":"633,1167,127,25","text":"Cheese"},{"boundingBox":"773,1170,247,25","text":"Manufacturers"},{"boundingBox":"1034,1173,95,23","text":"Blend"},{"boundingBox":"1143,1173,96,24","text":"50/50"},{"boundingBox":"1253,1173,18,22","text":"2"},{"boundingBox":"1286,1173,41,26","text":"Kg"}]}]},{"boundingBox":"1346,717,132,477","lines":[{"boundingBox":"1374,717,81,18","words":[{"boundingBox":"1374,717,81,18","text":"code"}]},{"boundingBox":"1361,792,97,19","words":[{"boundingBox":"1361,792,97,19","text":"52198"}]},{"boundingBox":"1362,836,99,19","words":[{"boundingBox":"1362,836,99,19","text":"21080"}]},{"boundingBox":"1363,881,100,20","words":[{"boundingBox":"1363,881,100,20","text":"98654"}]},{"boundingBox":"1364,927,100,19","words":[{"boundingBox":"1364,927,100,19","text":"44145"}]},{"boundingBox":"1346,973,123,21","words":[{"boundingBox":"1346,973,123,21","text":"106576"}]},{"boundingBox":"1347,1020,124,22","words":[{"boundingBox":"1347,1020,124,22","text":"130080"}]},{"boundingBox":"1368,1070,105,21","words":[{"boundingBox":"1368,1070,105,21","text":"22866"}]},{"boundingBox":"1391,1120,84,22","words":[{"boundingBox":"1391,1120,84,22","text":"7294"}]},{"boundingBox":"1350,1171,128,23","words":[{"boundingBox":"1350,1171,128,23","text":"115778"}]}]},{"boundingBox":"1801,764,357,41","lines":[{"boundingBox":"1801,764,357,41","words":[{"boundingBox":"1801,785,69,20","text":"83.2"},{"boundingBox":"1923,776,90,23","text":"151.3"},{"boundingBox":"2066,764,92,25","text":"166.4"}]}]},{"boundingBox":"1557,790,73,400","lines":[{"boundingBox":"1578,790,17,19","words":[{"boundingBox":"1578,790,17,19","text":"2"}]},{"boundingBox":"1582,834,17,18","words":[{"boundingBox":"1582,834,17,18","text":"1"}]},{"boundingBox":"1586,879,16,18","words":[{"boundingBox":"1586,879,16,18","text":"1"}]},{"boundingBox":"1557,924,50,19","words":[{"boundingBox":"1557,924,50,19","text":"2.5"}]},{"boundingBox":"1594,971,17,19","words":[{"boundingBox":"1594,971,17,19","text":"1"}]},{"boundingBox":"1597,1017,18,21","words":[{"boundingBox":"1597,1017,18,21","text":"3"}]},{"boundingBox":"1601,1068,18,19","words":[{"boundingBox":"1601,1068,18,19","text":"1"}]},{"boundingBox":"1606,1118,17,20","words":[{"boundingBox":"1606,1118,17,20","text":"1"}]},{"boundingBox":"1609,1169,21,21","words":[{"boundingBox":"1609,1169,21,21","text":"4"}]}]},{"boundingBox":"1658,789,122,401","lines":[{"boundingBox":"1664,789,67,19","words":[{"boundingBox":"1664,789,67,19","text":"75.7"}]},{"boundingBox":"1670,833,68,19","words":[{"boundingBox":"1670,833,68,19","text":"13.6"}]},{"boundingBox":"1674,878,70,20","words":[{"boundingBox":"1674,878,70,20","text":"37.0"}]},{"boundingBox":"1658,923,90,20","words":[{"boundingBox":"1658,923,90,20","text":"117.5"}]},{"boundingBox":"1663,970,91,20","words":[{"boundingBox":"1663,970,91,20","text":"170.1"}]},{"boundingBox":"1688,1018,73,20","words":[{"boundingBox":"1688,1018,73,20","text":"46.8"}]},{"boundingBox":"1694,1067,73,20","words":[{"boundingBox":"1694,1067,73,20","text":"11.4"}]},{"boundingBox":"1699,1116,74,22","words":[{"boundingBox":"1699,1116,74,22","text":"30.3"}]},{"boundingBox":"1705,1167,75,23","words":[{"boundingBox":"1705,1167,75,23","text":"36.9"}]}]},{"boundingBox":"1801,828,131,360","lines":[{"boundingBox":"1809,828,70,20","words":[{"boundingBox":"1809,828,70,20","text":"13.6"}]},{"boundingBox":"1815,873,71,21","words":[{"boundingBox":"1815,873,71,21","text":"37.0"}]},{"boundingBox":"1801,919,91,21","words":[{"boundingBox":"1801,919,91,21","text":"117.5"}]},{"boundingBox":"1807,965,93,22","words":[{"boundingBox":"1807,965,93,22","text":"170.1"}]},{"boundingBox":"1834,1013,75,22","words":[{"boundingBox":"1834,1013,75,22","text":"46.8"}]},{"boundingBox":"1842,1062,75,23","words":[{"boundingBox":"1842,1062,75,23","text":"11.4"}]},{"boundingBox":"1848,1112,77,24","words":[{"boundingBox":"1848,1112,77,24","text":"30.3"}]},{"boundingBox":"1856,1163,76,25","words":[{"boundingBox":"1856,1163,76,25","text":"36.9"}]}]},{"boundingBox":"1946,807,302,374","lines":[{"boundingBox":"2096,807,73,24","words":[{"boundingBox":"2096,807,73,24","text":"13.6"}]},{"boundingBox":"1952,820,70,22","words":[{"boundingBox":"1952,820,70,22","text":"13.6"}]},{"boundingBox":"2106,851,73,25","words":[{"boundingBox":"2106,851,73,25","text":"37.0"}]},{"boundingBox":"1959,865,73,23","words":[{"boundingBox":"1959,865,73,23","text":"37.0"}]},{"boundingBox":"1946,897,245,37","words":[{"boundingBox":"1946,910,94,24","text":"293.8"},{"boundingBox":"2094,897,97,27","text":"293.8"}]},{"boundingBox":"1955,944,247,37","words":[{"boundingBox":"1955,957,95,24","text":"170.1"},{"boundingBox":"2105,944,97,27","text":"170.1"}]},{"boundingBox":"1964,992,250,37","words":[{"boundingBox":"1964,1004,96,25","text":"140.3"},{"boundingBox":"2116,992,98,27","text":"140.3"}]},{"boundingBox":"1994,1054,77,24","words":[{"boundingBox":"1994,1054,77,24","text":"11.4"}]},{"boundingBox":"2159,1091,80,28","words":[{"boundingBox":"2159,1091,80,28","text":"30.3"}]},{"boundingBox":"2003,1104,77,25","words":[{"boundingBox":"2003,1104,77,25","text":"30.3"}]},{"boundingBox":"1990,1143,258,38","words":[{"boundingBox":"1990,1155,98,26","text":"147.7"},{"boundingBox":"2149,1143,99,29","text":"147.7"}]}]},{"boundingBox":"63,1410,1839,131","lines":[{"boundingBox":"1374,1410,278,34","words":[{"boundingBox":"1374,1414,36,30","text":"N"},{"boundingBox":"1438,1412,155,32","text":"OTE"},{"boundingBox":"1621,1410,31,32","text":"S"}]},{"boundingBox":"63,1483,1839,58","words":[{"boundingBox":"63,1483,36,34","text":"A"},{"boundingBox":"120,1485,185,38","text":"finance"},{"boundingBox":"323,1490,171,43","text":"charge"},{"boundingBox":"512,1492,53,34","text":"of"},{"boundingBox":"579,1495,122,35","text":"1.5%"},{"boundingBox":"722,1497,77,33","text":"will"},{"boundingBox":"820,1498,58,34","text":"be"},{"boundingBox":"898,1499,136,34","text":"made"},{"boundingBox":"1053,1507,58,26","text":"on"},{"boundingBox":"1132,1499,164,42","text":"unpaid"},{"boundingBox":"1319,1499,218,34","text":"balances"},{"boundingBox":"1557,1498,116,33","text":"after"},{"boundingBox":"1691,1496,60,34","text":"30"},{"boundingBox":"1770,1495,132,41","text":"days."}]}]}]}