{"language":"en","textAngle":0.0,"orientation":"Up","regions":[{"boundingBox":"409,423,451,1158","lines":[{"boundingBox":"413,423,134,32","words":[{"boundingBox":"413,432,62,23","text":"Roger"},{"boundingBox":"478,423,69,29","text":"Jordan"}]},{"boundingBox":"413,458,176,30","words":[{"boundingBox":"413,461,88,27","text":"Mathilda"},{"boundingBox":"508,458,81,22","text":"Avenue"}]},{"boundingBox":"412,474,303,45","words":[{"boundingBox":"412,490,115,29","text":"Sunnyvale,"},{"boundingBox":"535,480,102,27","text":"California"},{"boundingBox":"646,474,69,26","text":"93231"}]},{"boundingBox":"411,521,165,36","words":[{"boundingBox":"411,530,56,27","text":"(643)"},{"boundingBox":"475,521,101,28","text":"132-9843"}]},{"boundingBox":"411,747,426,46","words":[{"boundingBox":"411,760,108,33","text":"Some"},{"boundingBox":"534,751,190,38","text":"Company"},{"boundingBox":"731,749,81,24","text":"Invoice"},{"boundingBox":"820,747,17,22","text":"#"}]},{"boundingBox":"410,789,374,47","words":[{"boundingBox":"410,800,56,36","text":"c/o"},{"boundingBox":"481,797,110,33","text":"Some"},{"boundingBox":"606,789,79,40","text":"Guy"},{"boundingBox":"730,801,54,22","text":"Date"}]},{"boundingBox":"415,1005,135,27","words":[{"boundingBox":"415,1005,135,27","text":"Description"}]},{"boundingBox":"414,1083,390,30","words":[{"boundingBox":"414,1092,44,21","text":"Rice"},{"boundingBox":"465,1090,85,22","text":"Bubbles"},{"boundingBox":"558,1088,31,23","text":"P/c"},{"boundingBox":"597,1086,87,22","text":"Sachets"},{"boundingBox":"691,1085,28,21","text":"30"},{"boundingBox":"727,1084,15,21","text":"X"},{"boundingBox":"750,1083,54,26","text":"30gr"}]},{"boundingBox":"414,1133,419,29","words":[{"boundingBox":"414,1140,64,22","text":"Muffin"},{"boundingBox":"486,1139,36,22","text":"Mix"},{"boundingBox":"529,1138,62,21","text":"White"},{"boundingBox":"600,1136,49,26","text":"High"},{"boundingBox":"658,1135,52,22","text":"fibre"},{"boundingBox":"719,1134,40,23","text":"M/b"},{"boundingBox":"768,1133,28,21","text":"10"},{"boundingBox":"804,1133,29,26","text":"Kg"}]},{"boundingBox":"413,1183,447,31","words":[{"boundingBox":"413,1190,83,21","text":"Chicken"},{"boundingBox":"504,1189,38,25","text":"Pop"},{"boundingBox":"550,1188,44,21","text":"Ems"},{"boundingBox":"602,1187,71,21","text":"Breast"},{"boundingBox":"681,1185,55,22","text":"Bites"},{"boundingBox":"745,1183,55,23","text":"Devil"},{"boundingBox":"811,1184,12,21","text":"I"},{"boundingBox":"831,1183,29,26","text":"Kg"}]},{"boundingBox":"414,1235,295,25","words":[{"boundingBox":"414,1237,140,23","text":"Breadcrumbs"},{"boundingBox":"562,1235,63,22","text":"Panko"},{"boundingBox":"633,1236,41,21","text":"200"},{"boundingBox":"682,1235,27,21","text":"Gr"}]},{"boundingBox":"412,1287,199,26","words":[{"boundingBox":"412,1288,82,25","text":"Vinegar"},{"boundingBox":"500,1287,63,21","text":"White"},{"boundingBox":"570,1287,13,20","text":"4"},{"boundingBox":"591,1287,20,20","text":"Lt"}]},{"boundingBox":"411,1336,190,26","words":[{"boundingBox":"411,1336,82,26","text":"Topping"},{"boundingBox":"501,1336,51,21","text":"Lime"},{"boundingBox":"560,1336,12,21","text":"3"},{"boundingBox":"581,1336,20,21","text":"Lt"}]},{"boundingBox":"412,1385,395,27","words":[{"boundingBox":"412,1385,68,22","text":"Eclairs"},{"boundingBox":"488,1385,42,22","text":"Mini"},{"boundingBox":"539,1385,83,22","text":"Custard"},{"boundingBox":"631,1385,55,22","text":"Filled"},{"boundingBox":"695,1386,26,21","text":"62"},{"boundingBox":"730,1385,15,22","text":"X"},{"boundingBox":"754,1385,53,27","text":"15gr"}]},{"boundingBox":"409,1509,50,21","words":[{"boundingBox":"409,1509,50,21","text":"Total"}]},{"boundingBox":"411,1558,133,23","words":[{"boundingBox":"411,1558,83,22","text":"Balance"},{"boundingBox":"502,1559,42,22","text":"Due"}]}]},{"boundingBox":"1108,736,710,1007","lines":[{"boundingBox":"1111,736,95,23","words":[{"boundingBox":"1111,736,95,23","text":"101138"}]},{"boundingBox":"1108,785,201,30","words":[{"boundingBox":"1108,788,97,27","text":"January"},{"boundingBox":"1215,786,22,24","text":"1,"},{"boundingBox":"1246,785,63,22","text":"2012"}]},{"boundingBox":"1410,1073,56,22","words":[{"boundingBox":"1410,1073,56,22","text":"3.00"}]},{"boundingBox":"1409,1125,57,22","words":[{"boundingBox":"1409,1125,57,22","text":"1.00"}]},{"boundingBox":"1409,1177,57,22","words":[{"boundingBox":"1409,1177,57,22","text":"5.00"}]},{"boundingBox":"1410,1228,57,22","words":[{"boundingBox":"1410,1228,57,22","text":"1.00"}]},{"boundingBox":"1410,1280,56,22","words":[{"boundingBox":"1410,1280,56,22","text":"1.20"}]},{"boundingBox":"1411,1331,55,22","words":[{"boundingBox":"1411,1331,55,22","text":"1.60"}]},{"boundingBox":"1410,1383,57,22","words":[{"boundingBox":"1410,1383,57,22","text":"1.00"}]},{"boundingBox":"1244,1513,88,26","words":[{"boundingBox":"1244,1513,88,26","text":"$262.2"}]},{"boundingBox":"1302,1566,31,25","words":[{"boundingBox":"1302,1566,31,25","text":"$0"}]},{"boundingBox":"1422,1711,396,32","words":[{"boundingBox":"1422,1711,396,32","text":"ADDITIONAL"}]}]},{"boundingBox":"2231,1008,155,399","lines":[{"boundingBox":"2231,1008,155,28","words":[{"boundingBox":"2231,1008,93,24","text":"Pre-GST"},{"boundingBox":"2331,1014,55,22","text":"Total"}]},{"boundingBox":"2234,1092,59,22","words":[{"boundingBox":"2234,1092,59,22","text":"$72.9"}]},{"boundingBox":"2236,1140,59,23","words":[{"boundingBox":"2236,1140,59,23","text":"$34.6"}]},{"boundingBox":"2238,1190,59,22","words":[{"boundingBox":"2238,1190,59,22","text":"$87.4"}]},{"boundingBox":"2240,1237,46,22","words":[{"boundingBox":"2240,1237,46,22","text":"$3.4"}]},{"boundingBox":"2242,1286,59,23","words":[{"boundingBox":"2242,1286,59,23","text":"$10.4"}]},{"boundingBox":"2244,1334,58,23","words":[{"boundingBox":"2244,1334,58,23","text":"$15.7"}]},{"boundingBox":"2246,1383,60,24","words":[{"boundingBox":"2246,1383,60,24","text":"$34.3"}]}]},{"boundingBox":"1866,1705,184,32","lines":[{"boundingBox":"1866,1705,184,32","words":[{"boundingBox":"1866,1705,184,32","text":"NOTES"}]}]},{"boundingBox":"402,1768,1169,57","lines":[{"boundingBox":"402,1768,1169,57","words":[{"boundingBox":"402,1768,20,27","text":"A"},{"boundingBox":"430,1768,104,32","text":"finance"},{"boundingBox":"544,1773,100,37","text":"charge"},{"boundingBox":"655,1777,29,29","text":"of"},{"boundingBox":"694,1779,74,30","text":"1.5%"},{"boundingBox":"779,1782,49,28","text":"will"},{"boundingBox":"841,1782,37,30","text":"be"},{"boundingBox":"890,1785,89,29","text":"made"},{"boundingBox":"991,1792,39,23","text":"on"},{"boundingBox":"1044,1787,111,36","text":"unpaid"},{"boundingBox":"1169,1788,150,31","text":"balances"},{"boundingBox":"1332,1789,82,30","text":"after"},{"boundingBox":"1426,1789,42,30","text":"30"},{"boundingBox":"1481,1789,90,36","text":"days."}]}]}]}