{"language":"en","textAngle":0.0,"orientation":"Left","regions":[{"boundingBox":"599,59,899,2351","lines":[{"boundingBox":"599,59,256,77","words":[{"boundingBox":"599,59,119,52","text":"Roger"},{"boundingBox":"728,84,127,52","text":"Jordan"}]},{"boundingBox":"599,119,330,88","words":[{"boundingBox":"599,119,172,61","text":"Mathjlda"},{"boundingBox":"785,153,144,54","text":"Avenue"}]},{"boundingBox":"599,167,539,120","words":[{"boundingBox":"599,167,220,71","text":"Sunnyvale."},{"boundingBox":"834,207,177,59","text":"California"},{"boundingBox":"1027,239,111,48","text":"93231"}]},{"boundingBox":"600,226,308,81","words":[{"boundingBox":"600,226,107,54","text":"(643)"},{"boundingBox":"724,247,184,60","text":"132-9843"}]},{"boundingBox":"602,543,507,107","words":[{"boundingBox":"602,543,205,72","text":"Some"},{"boundingBox":"834,572,275,78","text":"Compan"}]},{"boundingBox":"600,617,489,102","words":[{"boundingBox":"600,617,109,55","text":"c/o"},{"boundingBox":"738,624,196,69","text":"Some"},{"boundingBox":"960,649,129,70","text":"Guy"}]},{"boundingBox":"1162,627,152,42","words":[{"boundingBox":"1162,627,116,40","text":"Invoice"},{"boundingBox":"1293,643,21,26","text":"#"}]},{"boundingBox":"1161,713,77,34","words":[{"boundingBox":"1161,713,77,34","text":"Date"}]},{"boundingBox":"613,932,156,39","words":[{"boundingBox":"613,932,156,39","text":"Details"}]},{"boundingBox":"612,1055,305,48","words":[{"boundingBox":"612,1055,103,36","text":"Flour"},{"boundingBox":"728,1060,92,33","text":"Plain"},{"boundingBox":"835,1062,20,33","text":"2"},{"boundingBox":"873,1064,44,39","text":"Kg"}]},{"boundingBox":"612,1149,342,35","words":[{"boundingBox":"612,1149,102,34","text":"Flour"},{"boundingBox":"728,1151,81,32","text":"Rice"},{"boundingBox":"825,1152,70,32","text":"500"},{"boundingBox":"908,1152,46,32","text":"Gr"}]},{"boundingBox":"611,1239,555,42","words":[{"boundingBox":"611,1241,102,40","text":"Soup"},{"boundingBox":"728,1241,151,33","text":"Chicken"},{"boundingBox":"895,1240,127,32","text":"Noodle"},{"boundingBox":"1036,1239,74,32","text":"2.15"},{"boundingBox":"1126,1240,40,36","text":"Kg"}]},{"boundingBox":"612,1319,848,53","words":[{"boundingBox":"612,1333,87,35","text":"Pork"},{"boundingBox":"713,1332,113,40","text":"Spare"},{"boundingBox":"842,1329,77,32","text":"Ribs"},{"boundingBox":"934,1327,59,32","text":"Full"},{"boundingBox":"1009,1326,86,31","text":"Plate"},{"boundingBox":"1109,1325,47,29","text":"Frz"},{"boundingBox":"1167,1323,76,36","text":"(app"},{"boundingBox":"1257,1321,76,35","text":"15kg"},{"boundingBox":"1346,1319,65,32","text":"Ctn)"},{"boundingBox":"1424,1319,36,33","text":"Kg"}]},{"boundingBox":"612,1404,678,61","words":[{"boundingBox":"612,1424,161,41","text":"Napkins"},{"boundingBox":"789,1421,19,32","text":"1"},{"boundingBox":"825,1419,54,39","text":"Ply"},{"boundingBox":"894,1414,107,34","text":"Lunch"},{"boundingBox":"1017,1411,87,37","text":"Light"},{"boundingBox":"1116,1408,74,31","text":"Blue"},{"boundingBox":"1203,1404,87,32","text":"5001s"}]},{"boundingBox":"613,1490,630,63","words":[{"boundingBox":"613,1515,129,38","text":"Plastic"},{"boundingBox":"756,1508,130,44","text":"Sporks"},{"boundingBox":"901,1493,239,47","text":"(alternatives)"},{"boundingBox":"1155,1490,88,31","text":"100's"}]},{"boundingBox":"612,1554,886,96","words":[{"boundingBox":"612,1613,115,37","text":"Paper"},{"boundingBox":"738,1598,108,37","text":"Towel"},{"boundingBox":"862,1590,95,39","text":"Hand"},{"boundingBox":"971,1577,174,43","text":"Advanced"},{"boundingBox":"1159,1573,66,33","text":"Soft"},{"boundingBox":"1237,1569,41,32","text":"HI"},{"boundingBox":"1293,1558,139,41","text":"Recycled"},{"boundingBox":"1445,1554,53,31","text":"Roll"}]},{"boundingBox":"612,1665,550,75","words":[{"boundingBox":"612,1703,128,37","text":"Butter"},{"boundingBox":"753,1693,56,36","text":"P/c"},{"boundingBox":"824,1682,150,38","text":"Portions"},{"boundingBox":"988,1670,66,39","text":"200"},{"boundingBox":"1068,1668,23,30","text":"X"},{"boundingBox":"1104,1665,58,35","text":"7gr"}]},{"boundingBox":"611,1730,731,103","words":[{"boundingBox":"611,1799,100,34","text":"Cous"},{"boundingBox":"725,1787,96,34","text":"Cous"},{"boundingBox":"836,1770,148,39","text":"Medium"},{"boundingBox":"1001,1740,217,52","text":"Mediterranei"},{"boundingBox":"1231,1733,61,35","text":"500"},{"boundingBox":"1304,1730,38,30","text":"Gr"}]},{"boundingBox":"613,1840,497,87","words":[{"boundingBox":"613,1885,154,42","text":"Pavlova"},{"boundingBox":"783,1871,106,35","text":"Large"},{"boundingBox":"904,1847,114,44","text":"Round"},{"boundingBox":"1034,1844,19,32","text":"1"},{"boundingBox":"1067,1840,43,36","text":"Kg"}]},{"boundingBox":"614,1911,625,112","words":[{"boundingBox":"614,1978,119,45","text":"Sticks"},{"boundingBox":"749,1956,179,48","text":"Monterey"},{"boundingBox":"938,1938,78,47","text":"Jack"},{"boundingBox":"1029,1926,129,39","text":"Cheese"},{"boundingBox":"1171,1911,68,35","text":"90's"}]},{"boundingBox":"616,1968,810,149","words":[{"boundingBox":"616,2075,122,42","text":"prawn"},{"boundingBox":"753,2051,118,45","text":"cutlet"},{"boundingBox":"884,2031,105,45","text":"21/25"},{"boundingBox":"1005,2001,175,57","text":"Marinated"},{"boundingBox":"1194,1988,95,40","text":"Garlic"},{"boundingBox":"1302,1979,44,33","text":"B/t"},{"boundingBox":"1359,1974,16,29","text":"1"},{"boundingBox":"1388,1968,38,34","text":"Kg"}]},{"boundingBox":"617,2116,424,98","words":[{"boundingBox":"617,2163,162,51","text":"Noodles"},{"boundingBox":"795,2135,152,50","text":"Hokkien"},{"boundingBox":"963,2124,20,32","text":"1"},{"boundingBox":"998,2116,43,36","text":"Kg"}]},{"boundingBox":"617,2217,376,94","words":[{"boundingBox":"617,2262,115,49","text":"Chick"},{"boundingBox":"745,2248,90,41","text":"Peas"},{"boundingBox":"849,2224,83,45","text":"2.55"},{"boundingBox":"948,2217,45,36","text":"Kg"}]},{"boundingBox":"623,2307,385,103","words":[{"boundingBox":"623,2341,228,69","text":"Blueberries"},{"boundingBox":"865,2321,49,45","text":"Iqf"},{"boundingBox":"928,2316,20,33","text":"1"},{"boundingBox":"964,2307,44,37","text":"Kg"}]}]},{"boundingBox":"1565,670,225,1526","lines":[{"boundingBox":"1572,670,106,37","words":[{"boundingBox":"1572,670,106,37","text":"101138"}]},{"boundingBox":"1565,749,225,45","words":[{"boundingBox":"1565,749,112,41","text":"January"},{"boundingBox":"1689,759,22,31","text":"1,"},{"boundingBox":"1724,762,66,32","text":"2012"}]},{"boundingBox":"1661,983,74,27","words":[{"boundingBox":"1661,983,74,27","text":"code"}]},{"boundingBox":"1662,1084,50,28","words":[{"boundingBox":"1662,1084,50,28","text":"265"}]},{"boundingBox":"1663,1161,86,27","words":[{"boundingBox":"1663,1161,86,27","text":"73974"}]},{"boundingBox":"1664,1236,102,29","words":[{"boundingBox":"1664,1236,102,29","text":"124996"}]},{"boundingBox":"1663,1313,85,30","words":[{"boundingBox":"1663,1313,85,30","text":"83517"}]},{"boundingBox":"1663,1387,86,30","words":[{"boundingBox":"1663,1387,86,30","text":"10804"}]},{"boundingBox":"1663,1462,85,31","words":[{"boundingBox":"1663,1462,85,31","text":"73232"}]},{"boundingBox":"1664,1536,102,34","words":[{"boundingBox":"1664,1536,102,34","text":"109843"}]},{"boundingBox":"1665,1612,102,35","words":[{"boundingBox":"1665,1612,102,35","text":"108329"}]},{"boundingBox":"1666,1688,102,35","words":[{"boundingBox":"1666,1688,102,35","text":"140281"}]},{"boundingBox":"1667,1765,86,36","words":[{"boundingBox":"1667,1765,86,36","text":"54101"}]},{"boundingBox":"1670,1839,103,39","words":[{"boundingBox":"1670,1839,103,39","text":"109838"}]},{"boundingBox":"1672,1916,103,40","words":[{"boundingBox":"1672,1916,103,40","text":"126964"}]},{"boundingBox":"1676,1993,103,42","words":[{"boundingBox":"1676,1993,103,42","text":"159251"}]},{"boundingBox":"1680,2073,87,41","words":[{"boundingBox":"1680,2073,87,41","text":"79266"}]},{"boundingBox":"1685,2153,86,43","words":[{"boundingBox":"1685,2153,86,43","text":"87137"}]}]},{"boundingBox":"1922,994,113,1150","lines":[{"boundingBox":"1922,994,113,28","words":[{"boundingBox":"1922,994,113,28","text":"Ordered"}]},{"boundingBox":"1923,1090,13,27","words":[{"boundingBox":"1923,1090,13,27","text":"3"}]},{"boundingBox":"1922,1163,15,26","words":[{"boundingBox":"1922,1163,15,26","text":"4"}]},{"boundingBox":"1923,1236,13,25","words":[{"boundingBox":"1923,1236,13,25","text":"1"}]},{"boundingBox":"1923,1308,13,26","words":[{"boundingBox":"1923,1308,13,26","text":"1"}]},{"boundingBox":"1923,1380,36,26","words":[{"boundingBox":"1923,1380,36,26","text":"1.7"}]},{"boundingBox":"1923,1452,37,26","words":[{"boundingBox":"1923,1452,37,26","text":"1.5"}]},{"boundingBox":"1923,1526,13,26","words":[{"boundingBox":"1923,1526,13,26","text":"2"}]},{"boundingBox":"1923,1597,38,29","words":[{"boundingBox":"1923,1597,38,29","text":"2.5"}]},{"boundingBox":"1925,1671,14,27","words":[{"boundingBox":"1925,1671,14,27","text":"3"}]},{"boundingBox":"1927,1743,14,28","words":[{"boundingBox":"1927,1743,14,28","text":"3"}]},{"boundingBox":"1930,1817,13,27","words":[{"boundingBox":"1930,1817,13,27","text":"3"}]},{"boundingBox":"1932,1891,14,27","words":[{"boundingBox":"1932,1891,14,27","text":"5"}]},{"boundingBox":"1936,1962,38,30","words":[{"boundingBox":"1936,1962,38,30","text":"1.5"}]},{"boundingBox":"1941,2036,39,32","words":[{"boundingBox":"1941,2036,39,32","text":"0.3"}]},{"boundingBox":"1947,2117,14,27","words":[{"boundingBox":"1947,2117,14,27","text":"1"}]}]},{"boundingBox":"2157,1005,91,1096","lines":[{"boundingBox":"2158,1005,53,23","words":[{"boundingBox":"2158,1005,53,23","text":"Unit"}]},{"boundingBox":"2158,1097,50,27","words":[{"boundingBox":"2158,1097,12,27","text":"$"},{"boundingBox":"2172,1097,36,25","text":"4.0"}]},{"boundingBox":"2157,1165,50,28","words":[{"boundingBox":"2157,1165,50,28","text":"$2.0"}]},{"boundingBox":"2158,1234,63,28","words":[{"boundingBox":"2158,1234,63,28","text":"$35.0"}]},{"boundingBox":"2157,1303,64,28","words":[{"boundingBox":"2157,1303,64,28","text":"$27.0"}]},{"boundingBox":"2157,1371,64,29","words":[{"boundingBox":"2157,1371,64,29","text":"$11.0"}]},{"boundingBox":"2158,1440,49,30","words":[{"boundingBox":"2158,1440,49,30","text":"$3.0"}]},{"boundingBox":"2158,1507,63,31","words":[{"boundingBox":"2158,1507,63,31","text":"$18.0"}]},{"boundingBox":"2158,1576,64,32","words":[{"boundingBox":"2158,1576,64,32","text":"$23.0"}]},{"boundingBox":"2160,1646,49,31","words":[{"boundingBox":"2160,1646,49,31","text":"$3.0"}]},{"boundingBox":"2162,1713,63,33","words":[{"boundingBox":"2162,1713,63,33","text":"$18.0"}]},{"boundingBox":"2164,1782,63,34","words":[{"boundingBox":"2164,1782,63,34","text":"$29.0"}]},{"boundingBox":"2167,1851,65,36","words":[{"boundingBox":"2167,1851,65,36","text":"$22.0"}]},{"boundingBox":"2171,1923,50,35","words":[{"boundingBox":"2171,1923,50,35","text":"$3.0"}]},{"boundingBox":"2176,1994,50,35","words":[{"boundingBox":"2176,1994,50,35","text":"$6.0"}]},{"boundingBox":"2184,2062,64,39","words":[{"boundingBox":"2184,2062,64,39","text":"$13.0"}]}]},{"boundingBox":"2371,1102,85,959","lines":[{"boundingBox":"2373,1102,45,26","words":[{"boundingBox":"2373,1102,45,26","text":"$4.0"}]},{"boundingBox":"2372,1168,46,26","words":[{"boundingBox":"2372,1168,46,26","text":"$2.0"}]},{"boundingBox":"2372,1233,59,27","words":[{"boundingBox":"2372,1233,59,27","text":"$35.0"}]},{"boundingBox":"2371,1298,60,28","words":[{"boundingBox":"2371,1298,60,28","text":"$27.0"}]},{"boundingBox":"2371,1364,59,28","words":[{"boundingBox":"2371,1364,59,28","text":"$12.0"}]},{"boundingBox":"2371,1430,46,27","words":[{"boundingBox":"2371,1430,46,27","text":"$3.0"}]},{"boundingBox":"2371,1494,59,30","words":[{"boundingBox":"2371,1494,59,30","text":"$20.0"}]},{"boundingBox":"2371,1559,60,31","words":[{"boundingBox":"2371,1559,60,31","text":"$23.0"}]},{"boundingBox":"2374,1626,45,30","words":[{"boundingBox":"2374,1626,45,30","text":"$3.0"}]},{"boundingBox":"2375,1690,59,32","words":[{"boundingBox":"2375,1690,59,32","text":"$20.0"}]},{"boundingBox":"2378,1756,58,33","words":[{"boundingBox":"2378,1756,58,33","text":"$29.0"}]},{"boundingBox":"2381,1823,58,33","words":[{"boundingBox":"2381,1823,58,33","text":"$22.0"}]},{"boundingBox":"2385,1890,45,33","words":[{"boundingBox":"2385,1890,45,33","text":"9.0"}]},{"boundingBox":"2391,1958,45,34","words":[{"boundingBox":"2391,1958,45,34","text":"$6.0"}]},{"boundingBox":"2397,2024,59,37","words":[{"boundingBox":"2397,2024,59,37","text":"$13.0"}]}]},{"boundingBox":"2567,1023,75,933","lines":[{"boundingBox":"2571,1023,55,25","words":[{"boundingBox":"2571,1023,55,25","text":"price"}]},{"boundingBox":"2570,1106,56,25","words":[{"boundingBox":"2570,1106,56,25","text":"$11.0"}]},{"boundingBox":"2569,1169,44,25","words":[{"boundingBox":"2569,1169,44,25","text":"$8.0"}]},{"boundingBox":"2569,1232,55,24","words":[{"boundingBox":"2569,1232,55,24","text":"$35.0"}]},{"boundingBox":"2569,1295,55,26","words":[{"boundingBox":"2569,1295,35,26","text":"$27"},{"boundingBox":"2612,1295,12,16","text":"n"}]},{"boundingBox":"2568,1421,42,25","words":[{"boundingBox":"2568,1421,42,25","text":"$4.0"}]},{"boundingBox":"2568,1482,55,28","words":[{"boundingBox":"2568,1482,55,28","text":"$37.0"}]},{"boundingBox":"2567,1545,55,29","words":[{"boundingBox":"2567,1545,55,29","text":"$570"}]},{"boundingBox":"2569,1609,42,28","words":[{"boundingBox":"2569,1609,42,28","text":"$9.0"}]},{"boundingBox":"2570,1670,55,30","words":[{"boundingBox":"2570,1670,55,30","text":"$54.0"}]},{"boundingBox":"2573,1733,54,31","words":[{"boundingBox":"2573,1736,35,28","text":"$87"},{"boundingBox":"2616,1733,11,18","text":"n"}]},{"boundingBox":"2577,1795,65,34","words":[{"boundingBox":"2577,1795,65,34","text":"$108.0"}]},{"boundingBox":"2585,1926,42,30","words":[{"boundingBox":"2585,1926,42,30","text":"$2.0"}]}]},{"boundingBox":"2749,1231,53,266","lines":[{"boundingBox":"2751,1231,51,25","words":[{"boundingBox":"2751,1231,51,25","text":"$350"}]},{"boundingBox":"2749,1471,50,26","words":[{"boundingBox":"2749,1471,50,26","text":"gon"}]}]}]}